eevee/__init__.py
eevee/_run.py
eevee/_types.py
eevee/chatbot.py
eevee/color_logger.py
eevee/framework_models.py
eevee/messages.py
eevee/saved_chat.py
eevee/settings.py
eevee/tools.py
eevee/ui.py
eevee/utils.py
eevee/chat_connectors/__init__.py
eevee/chat_connectors/anthropic_connector.py
eevee/chat_connectors/connector_interface.py
eevee/chat_connectors/deepseek_connector.py
eevee/chat_connectors/google_connector.py
eevee/chat_connectors/mistral_connector.py
eevee/chat_connectors/openai_connector.py
eevee/resources/config.toml
eevee/resources/eevee_50.png
eevee_chat-0.0.3.dist-info/LICENSE
eevee_chat-0.0.3.dist-info/METADATA
eevee_chat-0.0.3.dist-info/WHEEL
eevee_chat-0.0.3.dist-info/entry_points.txt
eevee_chat-0.0.3.dist-info/top_level.txt
eevee_chat-0.0.3.dist-info/RECORD
