Metadata-Version: 2.1
Name: eevee-chat
Version: 0.0.3
Summary: A single chat interface for multiple LLMs
Home-page: http://shakedzy.xyz/eevee-chat
Download-URL: https://pypi.org/project/eevee-chat/
Author: Shaked Zychlinski
Author-email: shakedzy@gmail.com
License: CC BY-NC 4.0
Classifier: Programming Language :: Python :: 3.11
Classifier: Programming Language :: Python :: 3.12
Requires-Python: >=3.11
License-File: LICENSE
Requires-Dist: anthropic ~=0.21.3
Requires-Dist: beautifulsoup4 ~=4.12.3
Requires-Dist: duckduckgo-search ~=5.1.0
Requires-Dist: dynaconf ~=3.2.4
Requires-Dist: google-api-python-client ~=2.123.0
Requires-Dist: google-generativeai ~=0.4.1
Requires-Dist: gradio ==4.23.0
Requires-Dist: mistralai ~=0.1.6
Requires-Dist: openai ~=1.14.3
Requires-Dist: requests ~=2.31.0
Requires-Dist: tqdm ~=4.66.2
